iap_sdk/__init__.py
iap_sdk/client.py
iap_sdk/client_base.py
iap_sdk/modules/accounts.py
iap_sdk/modules/operations_manager.py
iap_sdk/modules/pronghorn_core.py
iap_sdk-2023.12a1.dist-info/LICENSE
iap_sdk-2023.12a1.dist-info/METADATA
iap_sdk-2023.12a1.dist-info/WHEEL
iap_sdk-2023.12a1.dist-info/top_level.txt
iap_sdk-2023.12a1.dist-info/RECORD
