Metadata-Version: 2.1
Name: iap_sdk
Version: 2023.12a1
Summary: Lightweight SDK to simplify the process of interacting with the Itential Automation Platform API.
Home-page: https://github.com/awetomate/itential-iap-sdk
Author: John Frauchiger
Author-email: john@awetomate.net
License: MIT
Project-URL: Documentation, https://github.com/awetomate/itential-iap-sdk
Project-URL: Source, https://github.com/awetomate/itential-iap-sdk
Classifier: Development Status :: 4 - Beta
Classifier: Intended Audience :: Developers
Classifier: Intended Audience :: Information Technology
Classifier: License :: OSI Approved :: MIT License
Classifier: Operating System :: OS Independent
Classifier: Programming Language :: Python :: 3.9
Classifier: Programming Language :: Python :: 3.10
Classifier: Programming Language :: Python :: 3.11
Classifier: Programming Language :: Python :: 3.12
Classifier: Topic :: Utilities
Requires-Python: >=3.9,<3.12
License-File: LICENSE
Requires-Dist: requests
